manyfesto/__init__.py
manyfesto/test_manyfesto.py
manyfesto-1.0.1.dist-info/METADATA
manyfesto-1.0.1.dist-info/WHEEL
manyfesto-1.0.1.dist-info/top_level.txt
manyfesto-1.0.1.dist-info/RECORD
