Metadata-Version: 2.1
Name: manyfesto
Version: 1.0.1
Summary: Manyfesto is a data-science tools for assigning key-value pairs to individual files using a series of simple rules.
Home-page: http://github.com/bigdelys/manyfesto
Author: Nima Bigdely-Shamlo, PhD
Author-email: nima.manyfesto@gmail.com
License: MIT
Keywords: data-science data science metadata yaml manifest
Platform: UNKNOWN
Classifier: Programming Language :: Python :: 3
Classifier: License :: OSI Approved :: MIT License
Classifier: Operating System :: OS Independent
Requires-Python: >=3.6
Requires-Dist: oyaml (>=0.9)
